dcei/__init__.py
dcei/py.typed
dceiref-2025.11.9.0.dist-info/METADATA
dceiref-2025.11.9.0.dist-info/WHEEL
dceiref-2025.11.9.0.dist-info/entry_points.txt
dceiref-2025.11.9.0.dist-info/RECORD
