Metadata-Version: 2.1
Name: dceiref
Version: 2025.11.9.0
Summary: Dataclass extension interface
Requires-Python: >=3.12
Requires-Dist: docnote>=2025.9.11.0
